SEILOV.cpython-38-x86_64-linux-gnu.so
SEILOV-0.1.dist-info/METADATA
SEILOV-0.1.dist-info/WHEEL
SEILOV-0.1.dist-info/top_level.txt
SEILOV-0.1.dist-info/RECORD
