Metadata-Version: 2.1
Name: SEILOV
Version: 0.1
Summary: My PyPI package
Home-page: UNKNOWN
Author: UNKNOWN
Author-email: UNKNOWN
License: UNKNOWN
Platform: UNKNOWN
